bond/__init__.py
bond/bond.py
bond/const.py
bond_home-0.0.9.dist-info/METADATA
bond_home-0.0.9.dist-info/WHEEL
bond_home-0.0.9.dist-info/top_level.txt
bond_home-0.0.9.dist-info/RECORD
