Metadata-Version: 2.1
Name: bond-home
Version: 0.0.9
Summary: Python library for controlling BOND Home Hub
Home-page: http://github.com/nguyer/bond-home
Author: Nicko Guyer
Author-email: nguyer@gmail.com
License: MIT
Platform: UNKNOWN
Requires-Dist: requests
